django_better_passwords/__init__.py
django_better_passwords/admin.py
django_better_passwords/apps.py
django_better_passwords/middleware.py
django_better_passwords/models.py
django_better_passwords/signals.py
django_better_passwords/tests.py
django_better_passwords/views.py
django_better_passwords/migrations/0001_initial.py
django_better_passwords/migrations/0002_auto_20240204_2224.py
django_better_passwords/migrations/__init__.py
django_better_passwords/validators/__init__.py
django_better_passwords/validators/custom_password_validator.py
django_better_passwords-0.2.dist-info/LICENSE
django_better_passwords-0.2.dist-info/METADATA
django_better_passwords-0.2.dist-info/WHEEL
django_better_passwords-0.2.dist-info/top_level.txt
django_better_passwords-0.2.dist-info/RECORD
