Metadata-Version: 2.1
Name: django-better-passwords
Version: 0.2
Summary: A Django app to provide tools to enforce stronger password policies and expiration.
Home-page: https://github.com/andrelccorrea/django-better-passwords
Author: André Corrêa
Author-email: André Corrêa <andre.lcosta@hotmail.com>
Maintainer-email: André Corrêa <andre.lcosta@hotmail.com>
License: BSD 3-Clause License
Keywords: password,auth,better,expiration
Requires-Python: >=3.7
License-File: LICENSE
Requires-Dist: Django >=2.0
